LICENSE
README.rst
pyproject.toml
setup.py
Promium.egg-info/PKG-INFO
Promium.egg-info/SOURCES.txt
Promium.egg-info/dependency_links.txt
Promium.egg-info/entry_points.txt
Promium.egg-info/requires.txt
Promium.egg-info/top_level.txt
doc/__init__.py
doc/conf.py
promium/__init__.py
promium/_diag.py
promium/assertions.py
promium/base.py
promium/browsers.py
promium/common.py
promium/device_config.py
promium/exceptions.py
promium/expected_conditions.py
promium/helpers.py
promium/logger.py
promium/plugin.py
promium/test_case.py
promium/waits.py
promium/elements/__init__.py
promium/elements/checkbox.py
promium/elements/drop_downs.py
promium/elements/frame.py
promium/elements/input_field.py
promium/elements/link.py
promium/elements/multiselect_listbox.py
promium/elements/radio_button.py
promium/elements/textarea_field.py
promium/elements/upload_button.py
promium/support/__init__.py
promium/support/settings.py
tests/__init__.py
tests/config.py
tests/conftest.py
tests/test_catalog_404.py
tests/test_catalog_gallery.py
tests/test_enviroment.py
tests/test_exceptions.py
tests/test_expected_conditions.py
tests/test_helpers.py
tests/test_requests.py
tests/test_soft_asserts.py
tests/test_test_cases.py
tests/test_waits.py
tests/urls.py
tests/pages/__init__.py
tests/pages/catalog_404_page.py
tests/pages/catalog_gallery_page.py
tests/settings/__init__.py
tests/settings/test_base.py
tests/settings/test_chrome.py
tests/settings/test_edge.py
tests/settings/test_firefox.py
tests/settings/test_ie.py
tests/settings/test_opera.py