Metadata-Version: 2.1
Name: Promium
Version: 3.7.7
Summary: Selenium wrapper for testing Web UI
Author: Denis Korytkin, Nataliia Guieva, Roman Zaporozhets, Vladimir Kritov, Oleh Dykusha
Project-URL: Home page, https://none
Project-URL: Documentation, https://none
Keywords: Testing UI,Selenium,PageObject,Selenium wrapper
Platform: linux
Classifier: Programming Language :: Python :: 3.13
Classifier: Topic :: Software Development :: Libraries :: Python Modules
Classifier: Topic :: Software Development :: Libraries :: Application Frameworks
Classifier: Topic :: Software Development :: Testing
Classifier: Development Status :: 4 - Beta
Classifier: License :: OSI Approved :: MIT License
Requires-Python: >=3.10,<4
License-File: LICENSE
Requires-Dist: six>=1.10.0
Requires-Dist: json_checker>=1.2.1
Requires-Dist: urllib3>=2.0.2
Requires-Dist: py>=1.5.2
Requires-Dist: pytest>=5.0.0
Requires-Dist: pytest_rerunfailures>=4.1.0
Requires-Dist: pytest-forked>=0.2
Requires-Dist: pytest-instafail>=0.3.0
Requires-Dist: deepdiff>=5.7.0
Requires-Dist: selenium>=4.10.0
